hypersphere/__init__.py
hypersphere/pca.py
hypersphere/spheric.py
hypersphere/visualization.py
hypersphere-0.1.3.dist-info/METADATA
hypersphere-0.1.3.dist-info/WHEEL
hypersphere-0.1.3.dist-info/RECORD
