Metadata-Version: 2.1
Name: hypersphere
Version: 0.1.3
Summary: Проект для работы с данными, распределенными на поверхности гиперсферы.
Author: Radik Ismagilov
Author-email: radik@td.ru
Requires-Python: >=3.10,<3.11
Classifier: Programming Language :: Python :: 3
Classifier: Programming Language :: Python :: 3.10
Requires-Dist: ipympl (==0.9.3)
Requires-Dist: matplotlib (==3.8.0)
Requires-Dist: nbformat (==4.2.0)
Requires-Dist: numpy (>=1.24,<2.0)
Requires-Dist: plotly (>=5.18.0,<6.0.0)
Requires-Dist: scikit-learn (>=1.3.1,<2.0.0)
Requires-Dist: setuptools (>=68.2.2,<69.0.0)
Requires-Dist: umap-learn[plot] (>=0.5.4,<0.6.0)
